ai_edge_litert/__init__.py
ai_edge_litert/_pywrap_analyzer_wrapper.so
ai_edge_litert/_pywrap_litert_compiled_model_wrapper.so
ai_edge_litert/_pywrap_litert_converter.so
ai_edge_litert/_pywrap_litert_interpreter_wrapper.so
ai_edge_litert/_pywrap_litert_tensor_buffer_wrapper.so
ai_edge_litert/_pywrap_modify_model_interface.so
ai_edge_litert/_pywrap_string_util.so
ai_edge_litert/_pywrap_tensorflow_lite_calibration_wrapper.so
ai_edge_litert/_pywrap_tensorflow_lite_metrics_wrapper.so
ai_edge_litert/any_pb2.py
ai_edge_litert/api_pb2.py
ai_edge_litert/compiled_model.py
ai_edge_litert/descriptor_pb2.py
ai_edge_litert/duration_pb2.py
ai_edge_litert/empty_pb2.py
ai_edge_litert/field_mask_pb2.py
ai_edge_litert/format_converter_wrapper_pybind11.so
ai_edge_litert/hardware_accelerator.py
ai_edge_litert/interpreter.py
ai_edge_litert/libLiteRt.dylib
ai_edge_litert/libLiteRt.so
ai_edge_litert/libLiteRtMetalAccelerator.dylib
ai_edge_litert/libpywrap_litert_common.dylib
ai_edge_litert/metrics_interface.py
ai_edge_litert/metrics_portable.py
ai_edge_litert/model_runtime_info_pb2.py
ai_edge_litert/plugin_pb2.py
ai_edge_litert/profiling_info_pb2.py
ai_edge_litert/pywrap_genai_ops.so
ai_edge_litert/schema_py_generated.py
ai_edge_litert/source_context_pb2.py
ai_edge_litert/struct_pb2.py
ai_edge_litert/tensor_buffer.py
ai_edge_litert/timestamp_pb2.py
ai_edge_litert/type_pb2.py
ai_edge_litert/wrappers_pb2.py
ai_edge_litert/aot/__init__.py
ai_edge_litert/aot/aot_compile.py
ai_edge_litert/aot/prepare_for_npu.py
ai_edge_litert/aot/ai_pack/__init__.py
ai_edge_litert/aot/ai_pack/export_lib.py
ai_edge_litert/aot/core/__init__.py
ai_edge_litert/aot/core/apply_plugin.py
ai_edge_litert/aot/core/common.py
ai_edge_litert/aot/core/components.py
ai_edge_litert/aot/core/mlir_transforms.py
ai_edge_litert/aot/core/tflxx_util.py
ai_edge_litert/aot/core/types.py
ai_edge_litert/aot/vendors/__init__.py
ai_edge_litert/aot/vendors/fallback_backend.py
ai_edge_litert/aot/vendors/import_vendor.py
ai_edge_litert_nightly-2.2.0.dev20260131.dist-info/METADATA
ai_edge_litert_nightly-2.2.0.dev20260131.dist-info/WHEEL
ai_edge_litert_nightly-2.2.0.dev20260131.dist-info/top_level.txt
ai_edge_litert_nightly-2.2.0.dev20260131.dist-info/RECORD
